design_portfolio/data.py
design_portfolio/portfolios/__init__.py
design_portfolio/portfolios/porfolios2.py
design_portfolio/portfolios/porfolios3.py
design_portfolio/portfolios/portfolios1.py
design_portfolio-0.0.3.dist-info/LICENSE.txt
design_portfolio-0.0.3.dist-info/METADATA
design_portfolio-0.0.3.dist-info/WHEEL
design_portfolio-0.0.3.dist-info/top_level.txt
design_portfolio-0.0.3.dist-info/RECORD
