Metadata-Version: 2.1
Name: design-portfolio
Version: 0.0.3
Summary: Viet Nam stock profile
Home-page: https://github.com/nguyenbinh0807/profilevn.git
Author: nguyenthebinh
Author-email: 2054022009binh@ou.edu.vn
License: MIT
Keywords: markowitzvn,python
Classifier: Programming Language :: Python :: 3
Classifier: Intended Audience :: Developers
Classifier: License :: OSI Approved :: MIT License
Classifier: Operating System :: MacOS :: MacOS X
Classifier: Operating System :: Microsoft :: Windows
Classifier: Operating System :: OS Independent
License-File: LICENSE.txt
Requires-Dist: pandas (>=0.19.2)
Requires-Dist: numpy (>=1.20.2)
Requires-Dist: plotly (>=4.2.1)
Requires-Dist: scipy (>=1.2.0)
Requires-Dist: vnstock
Requires-Dist: requests
